sasm/__init__.py
sasm/assembler.py
sasm/instructions.py
sasm-0.2.1.data/scripts/sasm
sasm-0.2.1.dist-info/DESCRIPTION.rst
sasm-0.2.1.dist-info/METADATA
sasm-0.2.1.dist-info/RECORD
sasm-0.2.1.dist-info/WHEEL
sasm-0.2.1.dist-info/metadata.json
sasm-0.2.1.dist-info/top_level.txt
